AUTHORS
CHANGELOG.rst
LICENSE
MANIFEST.in
README.rst
setup.py
docs/Makefile
docs/conf.py
docs/getting_started.rst
docs/history.rst
docs/index.rst
docs/installing.rst
docs/make.bat
docs/misfit.rst
docs/notifications.rst
misfit/__init__.py
misfit/auth.py
misfit/cli.py
misfit/exceptions.py
misfit/misfit.py
misfit/notification.py
misfit.egg-info/PKG-INFO
misfit.egg-info/SOURCES.txt
misfit.egg-info/dependency_links.txt
misfit.egg-info/entry_points.txt
misfit.egg-info/requires.txt
misfit.egg-info/top_level.txt
requirements/base.txt
requirements/dev.txt
requirements/test.txt